sdmlib/__init__.py
sdmlib/sdmlib.py
sdmlib-0.1.2.dist-info/LICENSE
sdmlib-0.1.2.dist-info/METADATA
sdmlib-0.1.2.dist-info/WHEEL
sdmlib-0.1.2.dist-info/top_level.txt
sdmlib-0.1.2.dist-info/RECORD
