Metadata-Version: 2.1
Name: sdmlib
Version: 0.1.2
Summary: A fast, numpy-based implementation of Kanerva's Sparse     Distributed Memory (SDM)
Home-page: https://github.com/avandekleut/sdmlib
Author: Alex Van de Kleut
Author-email: avandekleut@gmail.com
License: UNKNOWN
Platform: UNKNOWN
Classifier: Programming Language :: Python :: 3
Classifier: License :: OSI Approved :: MIT License
Classifier: Operating System :: OS Independent
Requires-Python: >=3.7
Requires-Dist: numpy
Requires-Dist: scipy
